<?xml version="1.0" encoding="utf-8"?>
<rows>
	<row>
		<wid>490</wid>
		<ref_wid>490</ref_wid>
		<namekey>vendor.node</namekey>
		<folder>vendor</folder>
		<name>Vendor</name>
		<type>150</type>
		<publish>1</publish>
		<status>1</status>
		<params></params>
		<destination>node</destination>
		<parent>0</parent>
		<trans>1</trans>
		<certify>0</certify>
		<version>3665</version>
		<lversion>3665</lversion>
		<pref>1</pref>
		<rolid>1</rolid>
		<install></install>
		<ordering>867</ordering>
		<core>1</core>
		<modified>1436536370</modified>
		<reload>1</reload>
		<created>0</created>
		<showconfig>1</showconfig>
		<framework>0</framework>
	</row>	<row>
		<wid>1485</wid>
		<ref_wid>1485</ref_wid>
		<namekey>wishlist.node</namekey>
		<folder>wishlist</folder>
		<name>List of Items</name>
		<type>150</type>
		<publish>1</publish>
		<status>1</status>
		<params></params>
		<destination>node</destination>
		<parent>0</parent>
		<trans>1</trans>
		<certify>0</certify>
		<version>2294</version>
		<lversion>2294</lversion>
		<pref>0</pref>
		<rolid>1</rolid>
		<install></install>
		<ordering>784</ordering>
		<core>1</core>
		<modified>1436536376</modified>
		<reload>1</reload>
		<created>0</created>
		<showconfig>1</showconfig>
		<framework>0</framework>
	</row>	<row>
		<wid>1769</wid>
		<ref_wid>1769</ref_wid>
		<namekey>design.node</namekey>
		<folder>design</folder>
		<name>Design</name>
		<type>150</type>
		<publish>1</publish>
		<status>1</status>
		<params></params>
		<destination>node</destination>
		<parent>0</parent>
		<trans>1</trans>
		<certify>1</certify>
		<version>1728</version>
		<lversion>1728</lversion>
		<pref>1</pref>
		<rolid>1</rolid>
		<install></install>
		<ordering>143</ordering>
		<core>1</core>
		<modified>1436535695</modified>
		<reload>1</reload>
		<created>0</created>
		<showconfig>1</showconfig>
		<framework>0</framework>
	</row>
</rows>